sharqit/__init__.py
sharqit/libshrqt.so
sharqit/sharqit_base.cpython-310-x86_64-linux-gnu.so
sharqit/cpp/CMakeLists.txt
sharqit/cpp/Doxyfile
sharqit/cpp/Makefile
sharqit/cpp/TAGS
sharqit/cpp/binary_matrix.cpp
sharqit/cpp/binary_matrix.h
sharqit/cpp/dag.h
sharqit/cpp/dagcirc.cpp
sharqit/cpp/dagedge.cpp
sharqit/cpp/dagnode.cpp
sharqit/cpp/extract_qcirc.cpp
sharqit/cpp/fraction.cpp
sharqit/cpp/fraction.h
sharqit/cpp/linear_map.cpp
sharqit/cpp/linear_map.h
sharqit/cpp/merge_rotation.cpp
sharqit/cpp/nb_sharqit.cpp
sharqit/cpp/optimizer.cpp
sharqit/cpp/optimizer.h
sharqit/cpp/phase.cpp
sharqit/cpp/phase.h
sharqit/cpp/propagate_pauli_x.cpp
sharqit/cpp/qcirc.cpp
sharqit/cpp/qcirc.h
sharqit/cpp/qgate.cpp
sharqit/cpp/qgate.h
sharqit/cpp/sharqit.cpp
sharqit/cpp/sharqit.h
sharqit/cpp/simplify.cpp
sharqit/cpp/util.h
sharqit/cpp/zx.h
sharqit/cpp/zxdiagram.cpp
sharqit/cpp/zxnode.cpp
sharqit-0.2.3.dist-info/LICENSE
sharqit-0.2.3.dist-info/METADATA
sharqit-0.2.3.dist-info/WHEEL
sharqit-0.2.3.dist-info/top_level.txt
sharqit-0.2.3.dist-info/RECORD
