Metadata-Version: 2.1
Name: sharqit
Version: 0.2.3
Summary: Quantum Circuit Optimizer
Home-page: https://github.com/samn33/sharqit
Author: Sam.N
Author-email: saminriver33@gmail.com
License: MIT
Keywords: Quantum Computer,Quantum Circit,Optimization
Platform: UNKNOWN
Classifier: Development Status :: 4 - Beta
Classifier: Programming Language :: Python
Classifier: License :: OSI Approved :: MIT License
License-File: LICENSE
Requires-Dist: nanobind (>=1.9.2)
